JSON_log_formatter-0.2.0.dist-info/DESCRIPTION.rst
JSON_log_formatter-0.2.0.dist-info/METADATA
JSON_log_formatter-0.2.0.dist-info/RECORD
JSON_log_formatter-0.2.0.dist-info/WHEEL
JSON_log_formatter-0.2.0.dist-info/metadata.json
JSON_log_formatter-0.2.0.dist-info/top_level.txt
json_log_formatter/__init__.py
