Metadata-Version: 2.0
Name: JSON-log-formatter
Version: 0.2.0
Summary: JSON log formatter
Home-page: https://github.com/marselester/json-log-formatter
Author: Marsel Mavletkulov
Author-email: marselester@ya.ru
License: UNKNOWN
Platform: UNKNOWN
